orion_finance_sdk_py/__init__.py
orion_finance_sdk_py/__main__.py
orion_finance_sdk_py/cli.py
orion_finance_sdk_py/contracts.py
orion_finance_sdk_py/encrypt.py
orion_finance_sdk_py/types.py
orion_finance_sdk_py/utils.py
orion_finance_sdk_py/abis/LiquidityOrchestrator.json
orion_finance_sdk_py/abis/OrionConfig.json
orion_finance_sdk_py/abis/OrionTransparentVault.json
orion_finance_sdk_py/abis/TransparentVaultFactory.json
orion_finance_sdk_py/js_sdk/bundle.js
orion_finance_sdk_py/js_sdk/kms_lib_bg.wasm
orion_finance_sdk_py/js_sdk/tfhe_bg.wasm
orion_finance_sdk_py-1.1.0.dist-info/licenses/LICENSE
orion_finance_sdk_py-1.1.0.dist-info/METADATA
orion_finance_sdk_py-1.1.0.dist-info/WHEEL
orion_finance_sdk_py-1.1.0.dist-info/entry_points.txt
orion_finance_sdk_py-1.1.0.dist-info/top_level.txt
orion_finance_sdk_py-1.1.0.dist-info/RECORD
